{
  "playerPerms": {
    "54wolfman": {
      "uuid": "3f97bfa3-8301-48b9-9d2e-07b328671293",
      "worlds": {
        "skeeter_nether": [
          "darkseid"
        ],
        "newcity": [
          "darkseid"
        ],
        "survival_the_end": [
          "darkseid"
        ],
        "elytralobby": [
          "darkseid"
        ],
        "skywarslobby": [
          "darkseid"
        ],
        "parkourmedium": [
          "darkseid"
        ],
        "formuladrift": [
          "darkseid"
        ],
        "speedforce": [
          "darkseid"
        ],
        "fortressofsolitude": [
          "darkseid"
        ],
        "runner": [
          "darkseid"
        ],
        "turfwars": [
          "darkseid"
        ],
        "hurdles": [
          "darkseid"
        ],
        "metropolis": [
          "darkseid"
        ],
        "*": [
          "darkseid"
        ],
        "longparkour": [
          "darkseid"
        ],
        "mazerunner": [
          "darkseid"
        ],
        "spleef": [
          "darkseid"
        ],
        "parkourhub": [
          "darkseid"
        ],
        "towerparkour": [
          "darkseid"
        ],
        "boatrace": [
          "darkseid"
        ],
        "pvpworldsforest": [
          "darkseid"
        ],
        "escaperoom": [
          "darkseid"
        ],
        "lavahop": [
          "darkseid"
        ],
        "minecraftparkourmode": [
          "darkseid"
        ],
        "elytrapole": [
          "darkseid"
        ],
        "pvpworldsundergroundarmory": [
          "darkseid"
        ],
        "obstaclecourse": [
          "darkseid"
        ],
        "wooftywoo": [
          "darkseid"
        ],
        "parkoureasy": [
          "darkseid"
        ],
        "destructiblecity": [
          "darkseid"
        ],
        "vampirez": [
          "darkseid"
        ],
        "hilariousrace": [
          "darkseid"
        ],
        "pvpparkour": [
          "darkseid"
        ],
        "titanstower": [
          "darkseid"
        ],
        "straightlineparkour": [
          "darkseid"
        ],
        "waynemanor": [
          "darkseid"
        ],
        "parkourhard": [
          "darkseid"
        ],
        "colosseumlobby": [
          "darkseid"
        ],
        "garbageworld": [
          "darkseid"
        ],
        "splegg": [
          "darkseid"
        ],
        "torture": [
          "darkseid"
        ],
        "deathrun": [
          "darkseid"
        ],
        "deathmachine": [
          "darkseid"
        ],
        "waterprison": [
          "darkseid"
        ],
        "flyingbattlearena": [
          "darkseid"
        ],
        "sprintparkour": [
          "darkseid"
        ],
        "rollercoaster": [
          "darkseid"
        ],
        "rules": [
          "darkseid"
        ],
        "parksideprisonescape": [
          "darkseid"
        ],
        "pvpworldsruins": [
          "darkseid"
        ],
        "flyingbattlelobby": [
          "darkseid"
        ],
        "elytraeasy": [
          "darkseid"
        ],
        "gotham": [
          "darkseid"
        ],
        "megaparkour": [
          "darkseid"
        ],
        "godlyparkour": [
          "darkseid"
        ],
        "chess": [
          "darkseid"
        ],
        "hallofjustice": [
          "darkseid"
        ],
        "marathon": [
          "darkseid"
        ],
        "survival": [
          "darkseid"
        ],
        "techcombatknockbackgame": [
          "darkseid"
        ],
        "anarchy": [
          "darkseid"
        ],
        "elytrahard": [
          "darkseid"
        ],
        "underworld": [
          "darkseid"
        ],
        "verticalparkour": [
          "darkseid"
        ],
        "extremesumo": [
          "darkseid"
        ],
        "newminigamehub": [
          "darkseid"
        ],
        "skeeter_the_end": [
          "darkseid"
        ],
        "checkers": [
          "darkseid"
        ],
        "quickparkour": [
          "darkseid"
        ],
        "flappybirdparkour": [
          "darkseid"
        ],
        "deathdrop": [
          "darkseid"
        ],
        "skywars": [
          "darkseid"
        ],
        "survival_nether": [
          "darkseid"
        ],
        "heroicparkour": [
          "darkseid"
        ],
        "lasertag": [
          "darkseid"
        ],
        "initiation": [
          "darkseid"
        ],
        "alpha": [
          "darkseid"
        ],
        "pvpparkourlobby": [
          "darkseid"
        ],
        "infiniteparkour": [
          "darkseid"
        ],
        "turbotowers": [
          "darkseid"
        ],
        "colosseum": [
          "darkseid"
        ],
        "soccer": [
          "darkseid"
        ],
        "greenfield": [
          "darkseid"
        ],
        "spleeflobby": [
          "darkseid"
        ],
        "wallenpole": [
          "darkseid"
        ],
        "kingoftheladder": [
          "darkseid"
        ],
        "anarchy_nether": [
          "darkseid"
        ],
        "skeeter": [
          "darkseid"
        ],
        "elytramedium": [
          "darkseid"
        ],
        "elytrapvp": [
          "darkseid"
        ],
        "shortparkour": [
          "darkseid"
        ],
        "plots": [
          "darkseid"
        ],
        "overvoid": [
          "darkseid"
        ],
        "spawn": [
          "darkseid"
        ],
        "temple": [
          "darkseid"
        ],
        "pvpworldslobby": [
          "darkseid"
        ],
        "infinitycity": [
          "darkseid"
        ]
      }
    }
  }
}