{"SURVIVAL":{"potions":"[]","armorContents":{},"enderChestContents":{},"inventoryContents":{"3":{"==":"org.bukkit.inventory.ItemStack","type":"TNT"},"2":{"==":"org.bukkit.inventory.ItemStack","type":"ENDER_PORTAL_FRAME"},"1":{"==":"org.bukkit.inventory.ItemStack","type":"STONE"},"0":{"==":"org.bukkit.inventory.ItemStack","type":"DIAMOND_ORE"},"7":{"==":"org.bukkit.inventory.ItemStack","type":"ENDER_PEARL"},"6":{"==":"org.bukkit.inventory.ItemStack","type":"MINECART"},"5":{"==":"org.bukkit.inventory.ItemStack","type":"REDSTONE_TORCH_ON"},"4":{"==":"org.bukkit.inventory.ItemStack","type":"EYE_OF_ENDER","amount":20}},"stats":{"ex":"0.0","ra":"300","hp":"20","fl":"20","txp":"0","el":"0","sa":"5.0","ma":"300","xp":"0.0","ft":"-20","fd":"0.0"}}}