{"SURVIVAL":{"armorContents":{},"enderChestContents":{},"potions":"[]","inventoryContents":{"3":{"==":"org.bukkit.inventory.ItemStack","type":"SMOOTH_BRICK","damage":1},"2":{"==":"org.bukkit.inventory.ItemStack","type":"NETHER_FENCE"},"10":{"==":"org.bukkit.inventory.ItemStack","type":"SIGN"},"1":{"==":"org.bukkit.inventory.ItemStack","type":"LOG_2","damage":1},"0":{"==":"org.bukkit.inventory.ItemStack","type":"LEAVES_2","damage":1},"6":{"==":"org.bukkit.inventory.ItemStack","type":"WOOL","damage":1},"5":{"==":"org.bukkit.inventory.ItemStack","type":"POTION","damage":8270},"4":{"==":"org.bukkit.inventory.ItemStack","type":"SMOOTH_BRICK","damage":2},"11":{"==":"org.bukkit.inventory.ItemStack","type":"POWERED_RAIL"}},"stats":{"ra":"300","ex":"0.0043001175","hp":"20","fl":"20","txp":"0","el":"0","ma":"300","sa":"0.0","xp":"0.0","ft":"-20","fd":"0.0"}}}