{"SURVIVAL":{"enderChestContents":{},"potions":"[{\"pa\":3,\"pt\":23,\"pd\":9669},{\"pa\":3,\"pt\":5,\"pd\":199650},{\"pa\":127,\"pt\":3,\"pd\":199650}]","inventoryContents":{"0":{"==":"org.bukkit.inventory.ItemStack","type":"DIAMOND_PICKAXE","damage":806},"1":{"==":"org.bukkit.inventory.ItemStack","type":"DIAMOND_PICKAXE"},"2":{"==":"org.bukkit.inventory.ItemStack","type":"TORCH","amount":33},"3":{"==":"org.bukkit.inventory.ItemStack","type":"FLINT_AND_STEEL","damage":1},"4":{"==":"org.bukkit.inventory.ItemStack","type":"COBBLESTONE","amount":6},"5":{"==":"org.bukkit.inventory.ItemStack","type":"STONE","damage":1,"amount":2},"6":{"==":"org.bukkit.inventory.ItemStack","type":"ARROW","amount":2},"7":{"==":"org.bukkit.inventory.ItemStack","type":"ROTTEN_FLESH"}},"armorContents":{},"stats":{"ex":"3.735897","ma":"300","fl":"20","el":"0","xp":"0.0","hp":"20.0","txp":"0","sa":"20.0","ft":"-20","fd":"0.0","ra":"300"}}}